{
  "id": "f9de0e3e-338e-4e93-b4fb-7386b3179ebd",
  "name": "Amarthon",
  "sections": [
    {
      "id": "15a52757-2607-44ea-935c-5b45c9a8aceb",
      "title": "Character",
      "description": "",
      "accent": "#8b5cf6",
      "kind": "default",
      "scale": 1,
      "fields": [
        {
          "id": "461f84ac-8e98-4379-ad6f-ecc0f5f13a1e",
          "label": "Race",
          "type": "text",
          "value": "Variant Human",
          "description": ""
        },
        {
          "id": "e6fe4925-3d0e-46d8-a047-894308677fe3",
          "label": "Size",
          "type": "text",
          "value": "Medium",
          "description": ""
        },
        {
          "id": "e5306052-1164-4bbb-969d-da938ff6bacc",
          "label": "Class",
          "type": "text",
          "value": "Druid 8",
          "description": ""
        },
        {
          "id": "a1d93334-2ba7-4040-a588-d7c95a0c7c8f",
          "label": "Level",
          "type": "number",
          "value": "8",
          "description": "Character level. Use “Level up” in the toolbar to increment, then update HP max, hit dice, spell slots and features."
        },
        {
          "id": "4ad2b32e-f00d-4200-be37-31e0b19d84f9",
          "label": "Subclass",
          "type": "text",
          "value": "Circle of the Moon",
          "description": ""
        },
        {
          "id": "9bedd3ce-fca4-446c-95d2-acae819a2023",
          "label": "Background",
          "type": "text",
          "value": "Sage",
          "description": ""
        },
        {
          "id": "6fddb98d-6dd2-444f-aa13-0e1624a288f9",
          "label": "Primal Order",
          "type": "text",
          "value": "Magician",
          "description": ""
        },
        {
          "id": "75c27183-c5c7-4b32-8553-b3d538e3403a",
          "label": "Inspiration",
          "type": "boolean",
          "value": "false",
          "description": "Spend to reroll any d20. Toggle from the star in the toolbar."
        },
        {
          "id": "486fff43-4d5c-4064-997c-4433b97acb14",
          "label": "Armor",
          "type": "text",
          "value": "Light armor, Shields",
          "description": ""
        },
        {
          "id": "7196b49c-34b4-45cd-a873-fe31f089eb58",
          "label": "Weapons",
          "type": "text",
          "value": "Simple weapons",
          "description": ""
        },
        {
          "id": "1dfcf9bf-7eb1-41d2-a917-e7c230ed1879",
          "label": "Tools",
          "type": "text",
          "value": "Herbalism Kit, Calligrapher’s Supplies",
          "description": ""
        }
      ],
      "layout": {
        "x": 24,
        "y": 24,
        "w": 300,
        "h": 426
      }
    },
    {
      "id": "7edd0ecf-7bc7-48f9-b94d-d5900170a037",
      "title": "Ability Scores",
      "description": "",
      "accent": "#f59e0b",
      "kind": "abilities",
      "scale": 1,
      "fields": [
        {
          "id": "5ee1e024-8f78-4fd1-a6b4-728b6cdcd36f",
          "label": "STR",
          "type": "number",
          "value": "8",
          "description": ""
        },
        {
          "id": "755a96a3-27e7-4060-ba7b-71df645ba13d",
          "label": "DEX",
          "type": "number",
          "value": "14",
          "description": ""
        },
        {
          "id": "37414cff-5143-4159-952e-eb4ca9a68016",
          "label": "CON",
          "type": "number",
          "value": "17",
          "description": ""
        },
        {
          "id": "c74cfa7e-758e-43c9-9dc6-79b4431d0f96",
          "label": "INT",
          "type": "number",
          "value": "10",
          "description": ""
        },
        {
          "id": "516346c0-5afa-4eb4-b440-3c691d2c7cc7",
          "label": "WIS",
          "type": "number",
          "value": "19",
          "description": ""
        },
        {
          "id": "165ecba0-398a-43e4-a33c-684086c894a9",
          "label": "CHA",
          "type": "number",
          "value": "10",
          "description": ""
        },
        {
          "id": "ac621b0a-d3df-473f-b391-18ada430152b",
          "label": "STR Mod",
          "type": "computed",
          "value": "floor((str - 10) / 2)",
          "description": ""
        },
        {
          "id": "2793ffc7-61a4-4a2a-ac79-9d9aa0bdfe70",
          "label": "DEX Mod",
          "type": "computed",
          "value": "floor((dex - 10) / 2)",
          "description": ""
        },
        {
          "id": "901b7579-2d1b-4aef-8779-8f863d3837b5",
          "label": "CON Mod",
          "type": "computed",
          "value": "floor((con - 10) / 2)",
          "description": ""
        },
        {
          "id": "f8f231ce-82e1-4c9e-a8ae-ff58894a2c11",
          "label": "INT Mod",
          "type": "computed",
          "value": "floor((int - 10) / 2)",
          "description": ""
        },
        {
          "id": "b8987e85-81bf-49e3-a2fe-639f2c65c35c",
          "label": "WIS Mod",
          "type": "computed",
          "value": "floor((wis - 10) / 2)",
          "description": ""
        },
        {
          "id": "dec695bb-5162-419e-ac83-c1fc4c5556a2",
          "label": "CHA Mod",
          "type": "computed",
          "value": "floor((cha - 10) / 2)",
          "description": ""
        }
      ],
      "layout": {
        "x": 344,
        "y": 24,
        "w": 300,
        "h": 228
      }
    },
    {
      "id": "6d2cf28c-9fcf-4beb-b824-91dc7ace8ea7",
      "title": "Saving Throws",
      "description": "",
      "accent": "#8b5cf6",
      "kind": "skills",
      "scale": 1,
      "fields": [
        {
          "id": "2e1d0c4c-d93b-450a-92a9-5fe09d727272",
          "label": "Strength",
          "type": "number",
          "value": "",
          "description": "",
          "meta": {
            "ability": "STR",
            "prof": "none",
            "auto": "true"
          }
        },
        {
          "id": "77fb4730-8c72-4b29-ad39-992df297a1ce",
          "label": "Dexterity",
          "type": "number",
          "value": "",
          "description": "",
          "meta": {
            "ability": "DEX",
            "prof": "none",
            "auto": "true"
          }
        },
        {
          "id": "db47f0af-ae1b-44e7-9741-cdddb0d9d54b",
          "label": "Constitution",
          "type": "number",
          "value": "",
          "description": "",
          "meta": {
            "ability": "CON",
            "prof": "none",
            "auto": "true"
          }
        },
        {
          "id": "268faa2f-faae-4c90-92dd-330cea3364dc",
          "label": "Intelligence",
          "type": "number",
          "value": "",
          "description": "",
          "meta": {
            "ability": "INT",
            "prof": "proficient",
            "auto": "true"
          }
        },
        {
          "id": "0a8fc18d-bc92-4131-a6ba-2253fd6ae501",
          "label": "Wisdom",
          "type": "number",
          "value": "",
          "description": "",
          "meta": {
            "ability": "WIS",
            "prof": "proficient",
            "auto": "true"
          }
        },
        {
          "id": "f2656112-a398-4467-8d98-97811feb4351",
          "label": "Charisma",
          "type": "number",
          "value": "",
          "description": "",
          "meta": {
            "ability": "CHA",
            "prof": "none",
            "auto": "true"
          }
        }
      ],
      "layout": {
        "x": 664,
        "y": 24,
        "w": 300,
        "h": 276
      }
    },
    {
      "id": "648f71d4-c76b-413f-83a2-4cdbacd34281",
      "title": "Skills",
      "description": "",
      "accent": "#8b5cf6",
      "kind": "skills",
      "scale": 1,
      "fields": [
        {
          "id": "c030f4ad-c5d0-4686-83ec-e8462cc34e7c",
          "label": "Acrobatics",
          "type": "number",
          "value": "",
          "description": "",
          "meta": {
            "ability": "DEX",
            "prof": "none",
            "auto": "true"
          }
        },
        {
          "id": "53049b3a-9519-439e-8a31-a586ad0aa3ae",
          "label": "Animal Handling",
          "type": "number",
          "value": "",
          "description": "",
          "meta": {
            "ability": "WIS",
            "prof": "none",
            "auto": "true"
          }
        },
        {
          "id": "c2f706e4-fdc0-469a-8201-bb8f5ebe8a0a",
          "label": "Arcana",
          "type": "number",
          "value": "",
          "description": "",
          "meta": {
            "ability": "INT",
            "prof": "proficient",
            "auto": "true"
          }
        },
        {
          "id": "ac7df87a-0f4f-4403-a1f8-7cd967fc52fb",
          "label": "Athletics",
          "type": "number",
          "value": "",
          "description": "",
          "meta": {
            "ability": "STR",
            "prof": "none",
            "auto": "true"
          }
        },
        {
          "id": "51b0bee3-1859-4d3f-82ae-42c056f79276",
          "label": "Deception",
          "type": "number",
          "value": "",
          "description": "",
          "meta": {
            "ability": "CHA",
            "prof": "none",
            "auto": "true"
          }
        },
        {
          "id": "8ba04d0c-082c-47a2-96b9-4c5cf8582a5a",
          "label": "History",
          "type": "number",
          "value": "",
          "description": "",
          "meta": {
            "ability": "INT",
            "prof": "proficient",
            "auto": "true"
          }
        },
        {
          "id": "d8216213-eb7e-4299-bede-598740e856c2",
          "label": "Insight",
          "type": "number",
          "value": "",
          "description": "",
          "meta": {
            "ability": "WIS",
            "prof": "proficient",
            "auto": "true"
          }
        },
        {
          "id": "f917abd6-85ea-4e48-a30f-7b55e7739c99",
          "label": "Intimidation",
          "type": "number",
          "value": "",
          "description": "",
          "meta": {
            "ability": "CHA",
            "prof": "none",
            "auto": "true"
          }
        },
        {
          "id": "10c792a7-38e9-4dbd-9678-211470abf4d4",
          "label": "Investigation",
          "type": "number",
          "value": "",
          "description": "",
          "meta": {
            "ability": "INT",
            "prof": "none",
            "auto": "true"
          }
        },
        {
          "id": "9b9a5a42-b871-454b-8604-a9f0ca858e87",
          "label": "Medicine",
          "type": "number",
          "value": "",
          "description": "",
          "meta": {
            "ability": "WIS",
            "prof": "none",
            "auto": "true"
          }
        },
        {
          "id": "75eb0f24-55c5-4d34-b6f5-32fe55a4fbcb",
          "label": "Nature",
          "type": "number",
          "value": "",
          "description": "",
          "meta": {
            "ability": "INT",
            "prof": "proficient",
            "auto": "true"
          }
        },
        {
          "id": "56cd337c-2867-47c8-8c25-8b6fa0770e8e",
          "label": "Perception",
          "type": "number",
          "value": "",
          "description": "",
          "meta": {
            "ability": "WIS",
            "prof": "proficient",
            "auto": "true"
          }
        },
        {
          "id": "7364af1b-2349-43ad-8178-c301e253fb51",
          "label": "Performance",
          "type": "number",
          "value": "",
          "description": "",
          "meta": {
            "ability": "CHA",
            "prof": "none",
            "auto": "true"
          }
        },
        {
          "id": "dadd7bc9-fd24-4d6f-bb95-fc0570dd24c6",
          "label": "Persuasion",
          "type": "number",
          "value": "",
          "description": "",
          "meta": {
            "ability": "CHA",
            "prof": "none",
            "auto": "true"
          }
        },
        {
          "id": "9dae2856-9f7f-47a4-8b84-43fa98383aeb",
          "label": "Religion",
          "type": "number",
          "value": "",
          "description": "",
          "meta": {
            "ability": "INT",
            "prof": "none",
            "auto": "true"
          }
        },
        {
          "id": "46bbccd4-5784-4b7e-b2a1-354332561138",
          "label": "Sleight of Hand",
          "type": "number",
          "value": "",
          "description": "",
          "meta": {
            "ability": "DEX",
            "prof": "none",
            "auto": "true"
          }
        },
        {
          "id": "78b114a0-2908-4262-bf86-b62aa72d2b75",
          "label": "Stealth",
          "type": "number",
          "value": "",
          "description": "",
          "meta": {
            "ability": "DEX",
            "prof": "none",
            "auto": "true"
          }
        },
        {
          "id": "f726a96c-b3a7-4a44-ab27-e4b3b1b45fce",
          "label": "Survival",
          "type": "number",
          "value": "",
          "description": "",
          "meta": {
            "ability": "WIS",
            "prof": "none",
            "auto": "true"
          }
        }
      ],
      "layout": {
        "x": 984,
        "y": 24,
        "w": 300,
        "h": 636
      }
    },
    {
      "id": "0d3c23b1-b6e0-4642-8176-c9d4de78d060",
      "title": "Senses",
      "description": "",
      "accent": "#8b5cf6",
      "kind": "default",
      "scale": 1,
      "fields": [
        {
          "id": "8428ddbc-c525-4bb0-825e-62fe83d453fc",
          "label": "Passive Perception",
          "type": "computed",
          "value": "10 + wis_mod + proficiency",
          "description": ""
        },
        {
          "id": "ffd4501b-ea7d-4863-a6ce-881fd2be8560",
          "label": "Passive Insight",
          "type": "computed",
          "value": "10 + wis_mod + proficiency",
          "description": ""
        },
        {
          "id": "0dc8e07c-af83-49c4-a0a4-2902f6848913",
          "label": "Passive Investigation",
          "type": "computed",
          "value": "10 + int_mod",
          "description": ""
        }
      ],
      "layout": {
        "x": 344,
        "y": 272,
        "w": 300,
        "h": 186
      }
    },
    {
      "id": "5b0730a8-6d14-41a2-b090-df8b68cab3f5",
      "title": "Combat",
      "description": "",
      "accent": "#ef4444",
      "kind": "default",
      "scale": 1,
      "fields": [
        {
          "id": "4fbf6f80-7e5a-4995-9517-f016412c1349",
          "label": "AC",
          "type": "computed",
          "value": "max(barkskin * 16, 12 + dex_mod)",
          "description": "Studded Leather (base 12) + DEX mod; the Shield’s +2 comes from the Shield item’s effect, and Barkskin floors the armor AC to 16 while active."
        },
        {
          "id": "54051dc2-c469-4c36-9b81-1bda1794f807",
          "label": "Initiative",
          "type": "computed",
          "value": "dex_mod",
          "description": ""
        },
        {
          "id": "47aa50fd-976b-45e6-848f-1c6f225f8efa",
          "label": "Speed",
          "type": "number",
          "value": "30",
          "description": ""
        },
        {
          "id": "43825570-6df4-4d16-b22d-b07e065c24ef",
          "label": "Passive Perception",
          "type": "computed",
          "value": "10 + wis_mod + proficiency",
          "description": "Proficient in Perception."
        },
        {
          "id": "632f17f8-1ea9-4ab1-9bce-ac60aef2778d",
          "label": "Spell Save DC",
          "type": "computed",
          "value": "8 + proficiency + wis_mod",
          "description": "Druid spellcasting (Wisdom)."
        },
        {
          "id": "f836bfc3-c808-4c25-9cdc-9dca3d352283",
          "label": "Spell Attack",
          "type": "computed",
          "value": "proficiency + wis_mod",
          "description": ""
        },
        {
          "id": "d0d0ec71-1ddc-4480-a336-ee9008d03194",
          "label": "Proficiency",
          "type": "computed",
          "value": "floor((level - 1) / 4) + 2",
          "description": "Proficiency bonus, derived from your level. Used by attacks, saves, skills and spell DC."
        }
      ],
      "layout": {
        "x": 664,
        "y": 320,
        "w": 300,
        "h": 306
      }
    },
    {
      "id": "cc49f614-0cc5-46f7-937d-96ed7b9bc204",
      "title": "Hit Points",
      "description": "",
      "accent": "#10b981",
      "kind": "hp",
      "scale": 1,
      "fields": [
        {
          "id": "83031d4c-c363-4b70-9e55-f4c1a5a1cbf0",
          "label": "Current HP",
          "type": "number",
          "value": "67",
          "description": ""
        },
        {
          "id": "f72a3f25-b702-4c98-bdec-6e804f684dec",
          "label": "Max HP",
          "type": "number",
          "value": "67",
          "description": ""
        },
        {
          "id": "9ad24ef7-b53d-45d9-a58b-b6bd77a596c4",
          "label": "Temp HP",
          "type": "number",
          "value": "0",
          "description": ""
        },
        {
          "id": "eb1b6094-af49-4d4c-a483-9caef4ca8ddd",
          "label": "Resistances",
          "type": "text",
          "value": "",
          "description": "Comma-separated damage types halved on the Damage button."
        },
        {
          "id": "d9c38621-9c4f-425e-905f-fbda59be3f57",
          "label": "Vulnerabilities",
          "type": "text",
          "value": "",
          "description": "Comma-separated damage types doubled on the Damage button."
        },
        {
          "id": "68dad904-1b8e-4af1-83f4-8a3ba7693806",
          "label": "Hit Dice (d8)",
          "type": "resource",
          "value": "8",
          "description": "",
          "max": 8,
          "meta": {
            "die": "d8",
            "recharge": "long"
          }
        }
      ],
      "layout": {
        "x": 24,
        "y": 470,
        "w": 300,
        "h": 230
      }
    },
    {
      "id": "7eee9b1d-a96c-405d-a3d6-82b38a6ee539",
      "title": "Attacks",
      "description": "",
      "accent": "#f59e0b",
      "kind": "actions",
      "scale": 1,
      "fields": [
        {
          "id": "9d832676-fc41-45b8-ab08-4b18fcfffd82",
          "label": "Quarterstaff",
          "type": "text",
          "value": "",
          "description": "Strength-based two-handed 1d8. Toggle Shillelagh to use your spellcasting ability (WIS) and a 1d8 die instead. Topple mastery: on a hit the target makes a CON save (DC {8 + proficiency + wis_mod}) or falls Prone.",
          "meta": {
            "hit": "+{str_mod + proficiency}",
            "damage": "1d6+{str_mod}",
            "type": "bludgeoning",
            "range": "5 ft"
          },
          "toggles": [
            {
              "id": "971c917c-0e48-45b3-be1c-289e3d44c06c",
              "label": "Shillelagh",
              "active": false,
              "hitMode": "replace",
              "hit": "+{wis_mod + proficiency}",
              "parts": [
                {
                  "mode": "replace",
                  "damage": "1d8+{wis_mod}",
                  "type": "bludgeoning"
                }
              ],
              "setType": "",
              "description": "Cast Shillelagh: the staff uses your spellcasting ability (WIS) and deals 1d8."
            },
            {
              "id": "ad88b72f-1220-47ba-9b28-32d4cb15561a",
              "label": "Primal Strike",
              "active": false,
              "hitMode": "add",
              "hit": "",
              "parts": [
                {
                  "mode": "add",
                  "damage": "1d8",
                  "type": "bludgeoning"
                }
              ],
              "setType": "",
              "description": "Circle of the Moon: once per turn add 1d8 of the weapon’s damage type on a hit."
            }
          ]
        },
        {
          "id": "eb0bed8b-2e79-417a-9f75-77d51959d2fc",
          "label": "Longbow",
          "type": "text",
          "value": "",
          "description": "Slow mastery: on a hit, reduce the target’s Speed by 10 ft until your next turn.",
          "meta": {
            "hit": "+{dex_mod + proficiency}",
            "damage": "1d8+{dex_mod}",
            "type": "piercing",
            "range": "150/600"
          }
        },
        {
          "id": "86ea2f0f-8f75-45b6-a529-f530dc601bf9",
          "label": "Poison Spray (cantrip)",
          "type": "text",
          "value": "",
          "description": "Ranged 10 ft. Target makes a CON save vs your spell DC {8 + proficiency + wis_mod}; on a fail it takes the damage. Damage dice scale with your cantrip tier (from level).",
          "meta": {
            "damage": "{1 + floor((level + 1) / 6)}d12",
            "type": "poison",
            "range": "10 ft"
          }
        }
      ],
      "layout": {
        "x": 344,
        "y": 478,
        "w": 300,
        "h": 310
      }
    },
    {
      "id": "765e3f79-593e-482c-938c-df4c87b5428d",
      "title": "Spellcasting",
      "description": "",
      "accent": "#06b6d4",
      "kind": "default",
      "scale": 1,
      "fields": [
        {
          "id": "79f2a83f-592a-4936-a0fb-c6f55119e54e",
          "label": "Ability",
          "type": "text",
          "value": "Wisdom",
          "description": ""
        },
        {
          "id": "de42c222-ed82-4aa6-ba94-53429087c73e",
          "label": "Spell Save DC",
          "type": "computed",
          "value": "8 + proficiency + wis_mod",
          "description": ""
        },
        {
          "id": "33c6fdeb-13e5-4b5c-9392-bdb7af960873",
          "label": "Spell Attack",
          "type": "computed",
          "value": "proficiency + wis_mod",
          "description": ""
        },
        {
          "id": "b39a7b36-fb30-42db-87bf-c71192a20bfc",
          "label": "Prepared (class)",
          "type": "text",
          "value": "Druid — prepares from the whole Druid list",
          "description": "Circle of the Moon druids can swap prepared spells after a Long Rest."
        },
        {
          "id": "fac2cc9e-2620-4efe-82c8-15ea7672860a",
          "label": "Concentration",
          "type": "boolean",
          "value": "false",
          "description": "War Caster: Advantage on CON saves to maintain Concentration. Toggle on when concentrating."
        }
      ],
      "layout": {
        "x": 664,
        "y": 646,
        "w": 300,
        "h": 246
      }
    },
    {
      "id": "fedc68c6-917e-4019-8b32-f468dcbc808f",
      "title": "Spell Slots",
      "description": "",
      "accent": "#8b5cf6",
      "kind": "spellslots",
      "scale": 1,
      "fields": [
        {
          "id": "264cac0b-33a0-47b0-a33a-5e001f3d0f46",
          "label": "Level 1",
          "type": "resource",
          "value": "4",
          "description": "",
          "max": 4,
          "meta": {
            "recharge": "long"
          }
        },
        {
          "id": "637d809d-4c2f-4b18-b082-59d7e88db941",
          "label": "Level 2",
          "type": "resource",
          "value": "3",
          "description": "",
          "max": 3,
          "meta": {
            "recharge": "long"
          }
        },
        {
          "id": "982ccc7e-658b-4f18-b2b2-890cf1c63e82",
          "label": "Level 3",
          "type": "resource",
          "value": "3",
          "description": "",
          "max": 3,
          "meta": {
            "recharge": "long"
          }
        },
        {
          "id": "a9c764d3-acbd-43f9-af40-cbea5831f7e1",
          "label": "Level 4",
          "type": "resource",
          "value": "2",
          "description": "",
          "max": 2,
          "meta": {
            "recharge": "long"
          }
        }
      ],
      "layout": {
        "x": 984,
        "y": 680,
        "w": 300,
        "h": 232
      }
    },
    {
      "id": "1598f757-5aac-49fc-9f32-a9ef7b7eb4f6",
      "title": "Cantrips",
      "description": "",
      "accent": "#06b6d4",
      "kind": "default",
      "scale": 1,
      "fields": [
        {
          "id": "ef00a14d-fa2c-4aff-92bd-b4be4a60e478",
          "label": "Guidance",
          "type": "text",
          "value": "Druid",
          "description": "Concentration, 1 min. Touch a willing creature; add 1d4 to one ability check of its choice."
        },
        {
          "id": "c9245e69-a111-46cf-9316-5c3878d00bfa",
          "label": "Message",
          "type": "text",
          "value": "Druid",
          "description": "Whisper a message to a creature within 120 ft; it can reply."
        },
        {
          "id": "7a3ca4cd-39e0-4135-bcf5-d7aea90d4d61",
          "label": "Shillelagh",
          "type": "text",
          "value": "Druid",
          "description": "Bonus Action: your club/quarterstaff uses your spellcasting ability, deals 1d8, and counts as magical for 1 min."
        },
        {
          "id": "9965a516-10c9-4a48-9feb-209f934960a8",
          "label": "Poison Spray",
          "type": "text",
          "value": "Druid",
          "description": "CON save or take poison damage (scales with your cantrip tier). Range 10 ft."
        },
        {
          "id": "26d40d82-202c-4f4d-b5a0-0777b94887a0",
          "label": "Minor Illusion",
          "type": "text",
          "value": "Magic Initiate (Wizard)",
          "description": "Create a sound or image for 1 min."
        },
        {
          "id": "cf736734-4d6e-4172-946c-94c0d670b2a4",
          "label": "Booming Blade",
          "type": "text",
          "value": "Magic Initiate (Wizard)",
          "description": "Melee spell attack via a weapon; the target is sheathed in booming energy and takes thunder damage if it moves."
        }
      ],
      "layout": {
        "x": 24,
        "y": 720,
        "w": 300,
        "h": 276
      }
    },
    {
      "id": "0b3f72bd-0892-4611-9743-fa3cc37f2be6",
      "title": "Prepared Spells",
      "description": "",
      "accent": "#8b5cf6",
      "kind": "default",
      "scale": 1,
      "fields": [
        {
          "id": "ae697aec-4301-41b5-9727-26f7c345751b",
          "label": "— Level 1 —",
          "type": "text",
          "value": "",
          "description": ""
        },
        {
          "id": "9b714593-ba89-4b5d-99f7-7b4e29705803",
          "label": "Absorb Elements",
          "type": "text",
          "value": "1",
          "description": ""
        },
        {
          "id": "7ade5efd-fb36-41f1-8a98-79eeb534c96e",
          "label": "Detect Magic",
          "type": "text",
          "value": "1",
          "description": "Concentration · Ritual."
        },
        {
          "id": "9cf38f32-73ff-46e3-9358-eb159d1cae50",
          "label": "Healing Word",
          "type": "text",
          "value": "1",
          "description": "Bonus Action heal 2d4 + WIS mod at range."
        },
        {
          "id": "cfc8d42b-2104-4c81-84e2-3bbee6210648",
          "label": "Speak with Animals",
          "type": "text",
          "value": "1",
          "description": "Ritual · always prepared."
        },
        {
          "id": "138c7d72-8623-4cb2-8e77-f167bde272f9",
          "label": "Find Familiar",
          "type": "text",
          "value": "1",
          "description": "Ritual · via Wild Companion (spell slot or Wild Shape use)."
        },
        {
          "id": "89fce271-49b2-47bc-93ee-43491bbf88df",
          "label": "Shield",
          "type": "text",
          "value": "1",
          "description": "Magic Initiate: cast free 1/Long Rest, or with a slot. Reaction, +5 AC."
        },
        {
          "id": "1d028c79-ab87-4709-8891-ea2e579828e5",
          "label": "Silvery Barbs",
          "type": "text",
          "value": "1",
          "description": "Feat spell. Reaction to force a reroll of a hit/save/check."
        },
        {
          "id": "461a20ac-3b7e-41f6-84f9-f5e63eef1084",
          "label": "— Level 2 —",
          "type": "text",
          "value": "",
          "description": ""
        },
        {
          "id": "78e15b19-107f-4444-ad68-5156556b6b6a",
          "label": "Aid",
          "type": "text",
          "value": "2",
          "description": "Raise HP maximum and current HP by 5 for three creatures."
        },
        {
          "id": "156cfcb7-b3e6-4c03-bdba-88c3dc1cc9a3",
          "label": "Barkskin",
          "type": "text",
          "value": "2",
          "description": "Target’s AC can’t be less than 16."
        },
        {
          "id": "86a12b81-db1c-4557-a451-9ad0aadfdc38",
          "label": "Pass without Trace",
          "type": "text",
          "value": "2",
          "description": "Concentration. +10 to Stealth for the party."
        },
        {
          "id": "25787cf3-1b7c-4dc4-ba98-6f93cce54c39",
          "label": "Misty Step",
          "type": "text",
          "value": "2",
          "description": "Feat spell. Bonus Action teleport 30 ft."
        },
        {
          "id": "cc6f9e7e-dbce-4ddf-b831-ebf1be6c5ad3",
          "label": "— Level 3 —",
          "type": "text",
          "value": "",
          "description": ""
        },
        {
          "id": "87655a4d-1ae4-4174-8472-e9fd7f562339",
          "label": "Dispel Magic",
          "type": "text",
          "value": "3",
          "description": ""
        },
        {
          "id": "12e18e16-9da7-40bc-a062-ebca5b7778ee",
          "label": "Revivify",
          "type": "text",
          "value": "3",
          "description": "Return a creature dead < 1 min to life with 1 HP."
        },
        {
          "id": "91d455a2-8a59-4df0-9acd-a59655d77875",
          "label": "Syluné’s Viper",
          "type": "text",
          "value": "3",
          "description": ""
        },
        {
          "id": "91e64415-6713-4301-8d72-71603fd07ffd",
          "label": "— Level 4 —",
          "type": "text",
          "value": "",
          "description": ""
        },
        {
          "id": "a87d316d-0c58-40c4-905e-d575d727c1d1",
          "label": "Polymorph",
          "type": "text",
          "value": "4",
          "description": "Concentration."
        },
        {
          "id": "6a886f6d-9e0e-41c3-bf47-dc3a37a587f0",
          "label": "Wall of Fire",
          "type": "text",
          "value": "4",
          "description": "Concentration."
        },
        {
          "id": "b289c8b9-06e3-4f53-8833-0b262c3bff24",
          "label": "Fire Shield",
          "type": "text",
          "value": "4",
          "description": "Resistance to cold or fire; retaliate for 2d8."
        }
      ],
      "layout": {
        "x": 344,
        "y": 808,
        "w": 300,
        "h": 726
      }
    },
    {
      "id": "6c3e1515-1720-4684-9fda-ff052347983e",
      "title": "Resources",
      "description": "",
      "accent": "#ec4899",
      "kind": "default",
      "scale": 1,
      "fields": [
        {
          "id": "68cada7a-bae9-456f-8417-8518a685f498",
          "label": "Wild Shape",
          "type": "resource",
          "value": "3",
          "description": "",
          "max": 3,
          "meta": {
            "recharge": "short"
          }
        },
        {
          "id": "69b76eeb-1021-4303-9804-9f7d78174906",
          "label": "Moonlight Step",
          "type": "resource",
          "value": "4",
          "description": "",
          "max": 4,
          "meta": {
            "recharge": "long"
          }
        },
        {
          "id": "e8a2b0c3-2804-4438-99cc-1600ce943168",
          "label": "Shield (Magic Initiate)",
          "type": "resource",
          "value": "1",
          "description": "",
          "max": 1,
          "meta": {
            "recharge": "long"
          }
        }
      ],
      "layout": {
        "x": 664,
        "y": 912,
        "w": 300,
        "h": 186
      }
    },
    {
      "id": "dc0d99ef-5b70-485b-a472-20fc4a1667d1",
      "title": "Conditions",
      "description": "",
      "accent": "#ef4444",
      "kind": "conditions",
      "scale": 1,
      "fields": [
        {
          "id": "59af0620-29d7-454a-92cb-efacb54b04fa",
          "label": "Wild Shaped",
          "type": "boolean",
          "value": "false",
          "description": "Currently in a Beast form."
        },
        {
          "id": "3e08b228-8097-4686-b74c-478f1a393daf",
          "label": "Concentrating",
          "type": "boolean",
          "value": "false",
          "description": "War Caster: Advantage on CON saves to keep Concentration."
        },
        {
          "id": "ccb08edd-7b3d-4abd-8c70-d42c1c8d9422",
          "label": "Barkskin",
          "type": "boolean",
          "value": "false",
          "description": "AC floor 16 while active (the AC formula reads this)."
        },
        {
          "id": "3a64828c-c55b-4cfc-8015-5a916b14df65",
          "label": "Lantern Lit",
          "type": "boolean",
          "value": "false",
          "description": "Whale-Oil Lantern lit: Advantage on sight Perception in snow/fog/freezing rain.",
          "effects": [
            {
              "target": "perception",
              "op": "advantage",
              "value": "lit lantern in snow/fog"
            }
          ]
        },
        {
          "id": "54dd43d5-cd61-4adb-af51-5c90bbc52205",
          "label": "Bloodied",
          "type": "boolean",
          "value": "false",
          "description": "At or below half your Max HP. Auto-set by the HP tracker."
        },
        {
          "id": "bc913587-ef49-49f1-b292-b0db7d72144d",
          "label": "Prone",
          "type": "boolean",
          "value": "false",
          "description": ""
        },
        {
          "id": "116d8c80-160e-4b17-8749-3cbd34a0dc02",
          "label": "Grappled",
          "type": "boolean",
          "value": "false",
          "description": ""
        },
        {
          "id": "3f6ad91d-5193-4f8f-b8bf-ed670eb0de2a",
          "label": "Frightened",
          "type": "boolean",
          "value": "false",
          "description": ""
        },
        {
          "id": "6028bfa9-bec4-4ac2-85b4-9b7c2258cd78",
          "label": "Poisoned",
          "type": "boolean",
          "value": "false",
          "description": ""
        },
        {
          "id": "06a287b2-55f8-4372-a79f-ec3f8a15d9ab",
          "label": "Restrained",
          "type": "boolean",
          "value": "false",
          "description": ""
        },
        {
          "id": "14ff9b34-700e-424e-ab15-d4d1f37a2553",
          "label": "Stunned",
          "type": "boolean",
          "value": "false",
          "description": ""
        }
      ],
      "layout": {
        "x": 984,
        "y": 932,
        "w": 300,
        "h": 156
      }
    },
    {
      "id": "5fad1048-2332-4ceb-b601-130247277766",
      "title": "Features & Traits",
      "description": "",
      "accent": "#8b5cf6",
      "kind": "actions",
      "scale": 1,
      "fields": [
        {
          "id": "b821d409-c2e5-4e29-9cdc-1d1286848968",
          "label": "Druidic",
          "type": "text",
          "value": "",
          "description": "You know Druidic, the secret language of druids, and can leave hidden messages. You automatically spot such messages and can decipher them."
        },
        {
          "id": "14a5e7af-6e5d-4cd3-a471-6a2d907d1ef8",
          "label": "Primal Order — Magician",
          "type": "text",
          "value": "",
          "description": "You know one extra Druid cantrip (Poison Spray). Add your WIS mod (min +1) to your Intelligence (Arcana or Nature) checks.",
          "effects": [
            {
              "target": "arcana",
              "op": "add",
              "value": "wis_mod"
            },
            {
              "target": "nature",
              "op": "add",
              "value": "wis_mod"
            }
          ]
        },
        {
          "id": "0ddf85b6-ad9c-46bf-8ae5-b4092433a137",
          "label": "Wild Shape (3/rest)",
          "type": "text",
          "value": "",
          "description": "Bonus Action: transform into a known Beast form (max CR 1, no Fly Speed until — from level 8 you may take a form with a Fly Speed). Lasts hours = half your level. 3 uses at level 8; regain one on a Short Rest, all on a Long Rest."
        },
        {
          "id": "046b07e0-709c-4e54-88ae-0865b98b8077",
          "label": "Wild Companion",
          "type": "text",
          "value": "",
          "description": "Magic action: expend a spell slot or a Wild Shape use to cast Find Familiar without Materials; the familiar is Fey and lasts until your next Long Rest."
        },
        {
          "id": "0eb5f8b0-86aa-4b3f-a1aa-2facdbec3f9d",
          "label": "Circle Forms",
          "type": "text",
          "value": "",
          "description": "Circle of the Moon: while in Wild Shape you can use a Magic action to expend a spell slot and regain 1d8 HP per slot level; your beast forms may have higher CR. (See the subclass table for the CR cap.)"
        },
        {
          "id": "a968b01e-f03d-4f86-9bc6-4275eecfea29",
          "label": "Wild Resurgence",
          "type": "text",
          "value": "",
          "description": "Once per turn, if you have no Wild Shape uses left, expend a spell slot to regain one (no action). Also, once per Long Rest, expend a Wild Shape use to gain a level 1 spell slot."
        },
        {
          "id": "077a8759-4c9e-4e3d-8071-9ac498612199",
          "label": "Improved Circle Forms",
          "type": "text",
          "value": "",
          "description": "While in Wild Shape you can use your WIS mod in place of Con for concentration and add your WIS mod to the beast form’s attack damage; you also gain the ability to spend a slot to heal in beast form."
        },
        {
          "id": "52aa6b0f-45ca-414a-ab14-e3cab6d75323",
          "label": "Elemental Fury — Primal Strike",
          "type": "text",
          "value": "",
          "description": "Once on each of your turns when you hit with an attack roll (including in Wild Shape), deal an extra 1d8 damage of the attack’s type."
        },
        {
          "id": "b32ec58b-193e-4b3a-aaa4-1e2bb7687004",
          "label": "Moonlight Step (4/Long)",
          "type": "text",
          "value": "",
          "description": "Circle of the Moon: Bonus Action to teleport up to 30 ft to a space you can see; you have Advantage on your next attack this turn. WIS-mod uses per Long Rest; regain uses by expending a level 2+ slot."
        },
        {
          "id": "1410e0b3-127c-4e6f-87d1-a1efd02906d1",
          "label": "Spellcasting",
          "type": "text",
          "value": "",
          "description": "Wisdom-based druid casting. Prepare spells from the whole Druid list; swap after a Long Rest. Save DC 15, spell attack +7."
        },
        {
          "id": "e6e1eff7-609d-4dfa-b919-edce2e062655",
          "label": "War Caster (feat)",
          "type": "text",
          "value": "",
          "description": "Advantage on CON saves to maintain Concentration; cast somatic spells with hands full; cast a spell (1 action, single target) as an opportunity attack."
        },
        {
          "id": "b7d94963-cd8b-498e-a917-977af69404f5",
          "label": "Magic Initiate — Wizard (feat)",
          "type": "text",
          "value": "",
          "description": "Two wizard cantrips (Minor Illusion, Booming Blade) and a level 1 wizard spell (Shield) you can cast free 1/Long Rest or with slots."
        },
        {
          "id": "b3933bb0-3872-47ec-97cf-b618b45f8062",
          "label": "Homebrew feats",
          "type": "text",
          "value": "",
          "description": "Campaign feats: Dark Bargain, Runestones, Character Threads — grant Silvery Barbs and Misty Step among other benefits."
        }
      ],
      "layout": {
        "x": 24,
        "y": 1016,
        "w": 300,
        "h": 1130
      }
    },
    {
      "id": "996bf8ce-c8aa-41d8-8c70-b8fe3be58b1e",
      "title": "Languages",
      "description": "",
      "accent": "#8b5cf6",
      "kind": "default",
      "scale": 1,
      "fields": [
        {
          "id": "68861a3d-fee3-4b87-9c25-007b8cae5399",
          "label": "Common",
          "type": "text",
          "value": "fluent",
          "description": ""
        },
        {
          "id": "e37a5bac-22c5-4377-9203-9a5f64b701b2",
          "label": "Elvish",
          "type": "text",
          "value": "fluent",
          "description": ""
        },
        {
          "id": "93d7f545-a78e-40a6-a801-c12e5cdebd02",
          "label": "Druidic",
          "type": "text",
          "value": "fluent",
          "description": ""
        }
      ],
      "layout": {
        "x": 984,
        "y": 1108,
        "w": 300,
        "h": 186
      }
    },
    {
      "id": "e014fb2f-3050-4f1a-a2ae-51a15d45b4f8",
      "title": "Inventory",
      "description": "",
      "accent": "#a3a3a3",
      "kind": "inventory",
      "scale": 1,
      "fields": [
        {
          "id": "e4d676ef-7caf-420d-adca-79c2ece2ac57",
          "label": "GP",
          "type": "number",
          "value": "346",
          "description": "",
          "meta": {
            "coin": "gp"
          }
        },
        {
          "id": "5e0645ac-171b-452c-abc6-d5f77b843da3",
          "label": "SP",
          "type": "number",
          "value": "0",
          "description": "",
          "meta": {
            "coin": "sp"
          }
        },
        {
          "id": "d1354fd5-294a-420f-803c-1abe6ccc9f11",
          "label": "CP",
          "type": "number",
          "value": "0",
          "description": "",
          "meta": {
            "coin": "cp"
          }
        },
        {
          "id": "d13f984e-245c-4e15-8f2a-80f0f53923f7",
          "label": "Ring of Quick Recovery",
          "type": "text",
          "value": "worn",
          "description": "Adventurer’s Ring: when you regain hit points, regain an additional 3 (once per turn). Also sheds a cold, fuel-free flame (Bright Light 20 ft).",
          "effects": [
            {
              "target": "hp",
              "op": "note",
              "value": "When you regain HP, regain +3 more (1/turn)"
            }
          ]
        },
        {
          "id": "6807e14c-f4ff-400f-8f73-21994e042b20",
          "label": "Amulet — Beast Whisper",
          "type": "text",
          "value": "worn",
          "description": "Holy-symbol amulet: Advantage on Wisdom (Animal Handling) checks.",
          "effects": [
            {
              "target": "animal_handling",
              "op": "advantage",
              "value": "with beasts"
            }
          ]
        },
        {
          "id": "4cb311b8-bcba-47f2-92ad-8807adbc7e19",
          "label": "Quarterstaff — True Strike Echo",
          "type": "text",
          "value": "equipped",
          "description": "1/Long Rest, gain Advantage on one attack roll."
        },
        {
          "id": "a48d4eaa-8f79-4cd0-a021-0d6890a392e0",
          "label": "Spell Scroll — Fire Ball ×2",
          "type": "text",
          "value": "carried",
          "description": "Scroll casts Fire Ball (8d6). Save DC 13 / attack +5."
        },
        {
          "id": "69b7dfc0-89fb-4bf8-a901-cfa94888dca5",
          "label": "Spell Scroll — Counterspell ×2",
          "type": "text",
          "value": "carried",
          "description": ""
        },
        {
          "id": "f2abb15d-ae43-4eeb-9a0d-670e50987c60",
          "label": "Spell Scroll — Slow ×2",
          "type": "text",
          "value": "carried",
          "description": ""
        },
        {
          "id": "f1aab4c4-058e-481d-ab06-83a41370d0bc",
          "label": "Potion of Healing (Greater) ×3",
          "type": "text",
          "value": "carried",
          "description": "Regain 4d4 + 4 HP."
        },
        {
          "id": "859106c3-3ded-466c-ba3f-9a283c4efb98",
          "label": "Potion of Healing (Superior) ×4",
          "type": "text",
          "value": "carried",
          "description": "Regain 8d4 + 8 HP."
        },
        {
          "id": "9e5270a5-f52c-4ccc-8459-49578cc68c45",
          "label": "Deep North Expedition Cloak",
          "type": "text",
          "value": "worn",
          "description": "Resistance to environmental cold damage; Advantage on Survival checks to navigate/track/avoid getting lost in arctic terrain.",
          "effects": [
            {
              "target": "defenses",
              "op": "resist",
              "value": "cold"
            },
            {
              "target": "survival",
              "op": "advantage",
              "value": "arctic terrain"
            }
          ]
        },
        {
          "id": "7eb1eadf-63a0-4237-9951-5646fe297f36",
          "label": "Storm Hood of Kaldweave",
          "type": "text",
          "value": "worn",
          "description": "See through nonmagical blowing snow/fog/freezing rain; ranged attacks against you in such conditions take −2 to hit.",
          "effects": [
            {
              "target": "ac",
              "op": "note",
              "value": "Ranged attacks vs you take −2 in snow/fog/freezing rain"
            }
          ]
        },
        {
          "id": "76ac54d2-38c3-45e4-a75c-cd71b5ae7501",
          "label": "Whale-Oil Lantern Kit",
          "type": "text",
          "value": "carried",
          "description": "Flame can’t be extinguished by nonmagical wind/snow/rain; while lit, Advantage on sight Perception in snow/fog/freezing rain — toggle “Lantern Lit” to apply it."
        },
        {
          "id": "96c4fa23-7e33-4866-b3b9-614d0fe75c28",
          "label": "Studded Leather",
          "type": "text",
          "value": "worn",
          "description": "Light armor — base AC 12 + DEX mod."
        },
        {
          "id": "fb0cca76-613f-4129-b445-9209c0e8512e",
          "label": "Shield",
          "type": "text",
          "value": "worn",
          "description": "+2 AC.",
          "effects": [
            {
              "target": "ac",
              "op": "add",
              "value": "2"
            }
          ]
        },
        {
          "id": "52aadd66-55ab-4597-93e0-5a4b693511f1",
          "label": "Longbow + Arrows ×20",
          "type": "text",
          "value": "equipped",
          "description": ""
        },
        {
          "id": "25aaaa8f-8a1c-4cca-999c-6d7c5d6b6b38",
          "label": "Leather Armor (spare), Sickle",
          "type": "text",
          "value": "carried",
          "description": ""
        },
        {
          "id": "d30adcaa-73a4-4b26-847a-60d8fbe7b30d",
          "label": "Staff (arcane focus), Component Pouch",
          "type": "text",
          "value": "carried",
          "description": ""
        },
        {
          "id": "e21196a0-aaba-4620-8e88-af86aebc9f6e",
          "label": "Herbalism Kit, Healer’s Kit ×3",
          "type": "text",
          "value": "carried",
          "description": ""
        },
        {
          "id": "8b5a4cab-5140-4ecb-b47b-57836e8ab96f",
          "label": "Backpack, Bedroll, Tent, Waterskin",
          "type": "text",
          "value": "carried",
          "description": ""
        },
        {
          "id": "de96ecf8-7fa0-44c4-bb0f-e000e06e68a0",
          "label": "Rations ×5, Rope, Climber’s Kit, Pole",
          "type": "text",
          "value": "carried",
          "description": ""
        },
        {
          "id": "e4a5fc2b-de62-4e2b-a4c3-56462297bb85",
          "label": "Bullseye Lantern, Tinderbox, Torch ×10",
          "type": "text",
          "value": "carried",
          "description": ""
        },
        {
          "id": "bdf14de8-ad38-4fa0-bad1-09a2e9bd7b7b",
          "label": "Caltrops, Acid ×2, Antitoxin ×3",
          "type": "text",
          "value": "carried",
          "description": ""
        },
        {
          "id": "9fc1fafd-4571-4741-a5fe-fdcf70114171",
          "label": "Dynamite ×2, Blasting Powder ×5",
          "type": "text",
          "value": "carried",
          "description": ""
        },
        {
          "id": "16e947fb-05d8-4ac9-a7f4-e5a2d85e9ba9",
          "label": "Sled, Military Saddle, Piton",
          "type": "text",
          "value": "carried",
          "description": ""
        }
      ],
      "layout": {
        "x": 664,
        "y": 1118,
        "w": 300,
        "h": 876
      }
    }
  ]
}
